LICENCE.txt
README.rst
setup.cfg
setup.py
mfiles/__init__.py
mfiles/client.py
mfiles/definitions.py
mfiles/errors.py
mfiles.egg-info/PKG-INFO
mfiles.egg-info/SOURCES.txt
mfiles.egg-info/dependency_links.txt
mfiles.egg-info/requires.txt
mfiles.egg-info/top_level.txt
test/__init__.py
test/client_test.py